topsis_101803532/topsis_bhawi.py
TOPSIS_Bhawika_101803532-0.0.1.dist-info/LICENSE.txt
TOPSIS_Bhawika_101803532-0.0.1.dist-info/METADATA
TOPSIS_Bhawika_101803532-0.0.1.dist-info/WHEEL
TOPSIS_Bhawika_101803532-0.0.1.dist-info/entry_points.txt
TOPSIS_Bhawika_101803532-0.0.1.dist-info/top_level.txt
TOPSIS_Bhawika_101803532-0.0.1.dist-info/RECORD
